db_aggregator_api/__init__.py
db_aggregator_api/core.py
db_aggregator_api-0.2.0.dist-info/METADATA
db_aggregator_api-0.2.0.dist-info/WHEEL
db_aggregator_api-0.2.0.dist-info/top_level.txt
db_aggregator_api-0.2.0.dist-info/RECORD
