Metadata-Version: 2.4
Name: db_aggregator_api
Version: 0.2.0
Requires-Dist: requests
Dynamic: requires-dist
